graspit/__init__.py
graspit/center.py
graspit/handle_shipment.py
graspit/services/__init__.py
graspit/services/DBService/__init__.py
graspit/services/DBService/center.py
graspit/services/DBService/getThings.py
graspit/services/DBService/health.py
graspit/services/DBService/lifecycle.py
graspit/services/DBService/migration.py
graspit/services/DBService/models/__init__.py
graspit/services/DBService/models/config_base.py
graspit/services/DBService/models/dynamic_base.py
graspit/services/DBService/models/enums.py
graspit/services/DBService/models/result_base.py
graspit/services/DBService/models/types.py
graspit/services/DBService/sanic_free_shared.py
graspit/services/DBService/shared.py
graspit/services/Endpoints/__init__.py
graspit/services/Endpoints/center.py
graspit/services/Endpoints/errorHandling.py
graspit/services/Endpoints/oneliners.py
graspit/services/Endpoints/static_server.py
graspit/services/SchedularService/__init__.py
graspit/services/SchedularService/center.py
graspit/services/SchedularService/completeTestRun.py
graspit/services/SchedularService/constants.py
graspit/services/SchedularService/handlePending.py
graspit/services/SchedularService/lifecycle.py
graspit/services/SchedularService/modifySuites.py
graspit/services/SchedularService/pruneTasks.py
graspit/services/SchedularService/refer_types.py
graspit/services/SchedularService/shared.py
graspit-0.10.1.dist-info/entry_points.txt
graspit-0.10.1.dist-info/METADATA
graspit-0.10.1.dist-info/WHEEL
graspit-0.10.1.dist-info/RECORD
