Metadata-Version: 2.1
Name: graspit
Version: 0.10.1
Summary: service for working with your test results
License: MIT
Author: Rahul
Author-email: saihanumarahul66@gmail.com
Maintainer: Rahul
Maintainer-email: saihanumarahul66@gmail.com
Requires-Python: >=3.11,<4.0
Classifier: Development Status :: 4 - Beta
Classifier: Intended Audience :: Developers
Classifier: License :: OSI Approved :: MIT License
Classifier: Operating System :: OS Independent
Classifier: Programming Language :: Python :: 3
Classifier: Programming Language :: Python :: 3.11
Classifier: Topic :: Database :: Front-Ends
Provides-Extra: excel-export
Requires-Dist: APScheduler (>=3.10.4,<4.0.0)
Requires-Dist: click (>=8.1.7,<9.0.0)
Requires-Dist: loguru (>=0.7.2,<0.8.0)
Requires-Dist: pydantic (>=2.4.2,<3.0.0)
Requires-Dist: sanic (>=23.6.0,<24.0.0)
Requires-Dist: tortoise-orm (>=0.20.0,<0.21.0)
